Metadata-Version: 2.1
Name: modetheme
Version: 0.1.0
